{"record_id": "fae0f28f060217de", "original_url": "http://www.cargadetrabalhos.net/2017/07/19/webdesigner-e-multimedia-edicao-de-video/", "wayback_url": "https://arquivo.pt/noFrame/replay/20170731141855/https://www.cargadetrabalhos.net/page/3/", "arquivo_timestamp": "20170731141855", "year": 2017, "title": "webdesigner e multimédia (edição de vídeo)", "company": "", "location": "", "date_posted": "19 / Julho / 2017", "source": "cargadetrabalhos", "scraped_at_utc": "2026-05-03T21:15:39.032498+00:00"}