{
  "record_id": "6c9d8c70b80615df",
  "year": 2020,
  "title": "Cost Accountant - Industry",
  "company": "",
  "location": "",
  "date_posted": "16.01.2020",
  "original_url": "https://expressoemprego.pt/emprego/cost-accountant---industry/2001213",
  "wayback_url": "https://arquivo.pt/noFrame/replay/20200116180733/http://expressoemprego.pt/ofertas-emprego?page=2",
  "arquivo_timestamp": "20200116180733",
  "source": "neoexpresso",
  "scraped_at_utc": "2026-05-02T18:00:47.441224+00:00",
  "date_archived": "2020-01-16"
}