{
  "record_id": "a014a7b9b7b51302",
  "year": 2018,
  "title": "Junior Network Security Administrator",
  "company": "",
  "location": "",
  "date_posted": "17.07.2018",
  "original_url": "http://expressoemprego.pt/emprego/junior-network-security-administrator/1957356",
  "wayback_url": "https://arquivo.pt/noFrame/replay/20180611140705/http://expressoemprego.pt/ofertas-emprego?page=3",
  "arquivo_timestamp": "20180611140705",
  "source": "neoexpresso",
  "scraped_at_utc": "2026-05-02T17:59:39.667718+00:00",
  "date_archived": "2018-06-11"
}