{
  "record_id": "56b0d3941bdab709",
  "year": 2015,
  "title": "Técnico de Planeamento de Operações",
  "company": "",
  "location": "Cidade de Setúbal",
  "date_posted": "11 Out",
  "original_url": "http://expressoemprego.pt/emprego/tecnico-de-planeamento-de-operacoes/cidade-de-setubal/814631",
  "wayback_url": "https://arquivo.pt/noFrame/replay/20150129180257/http://expressoemprego.pt/ofertas-emprego?page=20",
  "arquivo_timestamp": "20150129180257",
  "source": "neoexpresso",
  "scraped_at_utc": "2026-05-02T17:54:32.924265+00:00",
  "date_archived": "2015-01-29"
}