{
  "record_id": "062884305d299a7b",
  "year": 2015,
  "title": "Técnico Comercial",
  "company": "",
  "location": "LISBOA, PORTO, COIMBRA e FARO",
  "date_posted": "25.04",
  "original_url": "http://expressoemprego.pt/emprego/tecnico-comercial/lisboa--porto--coimbra-e-faro/1146664",
  "wayback_url": "https://arquivo.pt/noFrame/replay/20150129180257/http://expressoemprego.pt/ofertas-emprego?page=5",
  "arquivo_timestamp": "20150129180257",
  "source": "neoexpresso",
  "scraped_at_utc": "2026-05-02T17:54:24.956532+00:00",
  "date_archived": "2015-01-29"
}