{
  "record_id": "72667dd3e05c950b",
  "year": 2015,
  "title": "Técnico Programador Reporting",
  "company": "Randstad Recursos Humanos",
  "location": "Lisboa - Centro Cidade",
  "date_posted": "14 Out",
  "original_url": "http://expressoemprego.pt/emprego/tecnico-programador-reporting/lisboa---centro-cidade/819722",
  "wayback_url": "https://arquivo.pt/noFrame/replay/20150129180257/http://expressoemprego.pt/ofertas-emprego?page=17",
  "arquivo_timestamp": "20150129180257",
  "source": "neoexpresso",
  "scraped_at_utc": "2026-05-02T17:54:32.277451+00:00",
  "date_archived": "2015-01-29"
}