{
  "record_id": "1a3508c09cb81b97",
  "year": 2015,
  "title": "Head Of Section Nike - Freeport",
  "company": "Randstad Professionals",
  "location": "Todo o país",
  "date_posted": "24.04",
  "original_url": "http://expressoemprego.pt/emprego/head-of-section-nike---freeport/todo-o-pais/1144847",
  "wayback_url": "https://arquivo.pt/noFrame/replay/20150129180257/http://expressoemprego.pt/ofertas-emprego?page=12",
  "arquivo_timestamp": "20150129180257",
  "source": "neoexpresso",
  "scraped_at_utc": "2026-05-02T17:54:29.634580+00:00",
  "date_archived": "2015-01-29"
}