{
  "record_id": "85e0b52cdcbd1d9a",
  "year": 2014,
  "title": "Estágio Curricular R&S",
  "company": "MSearch Finance & Banking",
  "location": "Lisboa",
  "date_posted": "08 Out",
  "original_url": "http://expressoemprego.pt/emprego/estagio-curricular-r-s/lisboa/812087",
  "wayback_url": "https://arquivo.pt/noFrame/replay/20140427173812/http://expressoemprego.pt/ofertas-emprego?page=5",
  "arquivo_timestamp": "20140427173812",
  "source": "neoexpresso",
  "scraped_at_utc": "2026-05-02T17:53:59.772907+00:00",
  "date_archived": "2014-04-27"
}