{
  "record_id": "a258465815effef3",
  "year": 2014,
  "title": "Engenheiro de Electrónica / Mecatrónica",
  "company": "Hays",
  "location": "Grande Lisboa",
  "date_posted": "25 Set",
  "original_url": "http://expressoemprego.pt/emprego/engenheiro-de-electronica---mecatronica/grande-lisboa/795895",
  "wayback_url": "https://arquivo.pt/noFrame/replay/20140427173812/http://expressoemprego.pt/ofertas-emprego?page=2",
  "arquivo_timestamp": "20140427173812",
  "source": "neoexpresso",
  "scraped_at_utc": "2026-05-02T17:53:59.092324+00:00",
  "date_archived": "2014-04-27"
}