{
  "record_id": "9a59b50896b43b5e",
  "year": 2016,
  "title": "Gestor de Clientes",
  "company": "",
  "location": "",
  "date_posted": "04.02.2016",
  "original_url": "http://expressoemprego.pt/emprego/gestor-de-clientes/lisboa/1226333",
  "wayback_url": "https://arquivo.pt/noFrame/replay/20160207081751/http://expressoemprego.pt/ofertas-emprego",
  "arquivo_timestamp": "20160207081751",
  "source": "neoexpresso",
  "scraped_at_utc": "2026-05-02T17:55:15.856995+00:00",
  "date_archived": "2016-02-07"
}