{
  "record_id": "186f9ce149d647b4",
  "year": 2016,
  "title": "Auditor Rh - Bem-Estar No Trabalho",
  "company": "",
  "location": "",
  "date_posted": "27.02.2017",
  "original_url": "https://expressoemprego.pt/emprego/auditor-rh---bem-estar-no-trabalho/sines/1859072",
  "wayback_url": "https://arquivo.pt/noFrame/replay/20160207081751/http://expressoemprego.pt/ofertas-emprego?page=13",
  "arquivo_timestamp": "20160207081751",
  "source": "neoexpresso",
  "scraped_at_utc": "2026-05-02T17:55:23.678513+00:00",
  "date_archived": "2016-02-07"
}