{
  "record_id": "22295a3d7379caa8",
  "year": 2016,
  "title": "Técnico Manutenção de AVAC - Lisboa",
  "company": "",
  "location": "",
  "date_posted": "27.02.2017",
  "original_url": "https://expressoemprego.pt/emprego/tecnico-manutencao-de-avac---lisboa/lisboa/1859073",
  "wayback_url": "https://arquivo.pt/noFrame/replay/20160207081751/http://expressoemprego.pt/ofertas-emprego?page=13",
  "arquivo_timestamp": "20160207081751",
  "source": "neoexpresso",
  "scraped_at_utc": "2026-05-02T17:55:23.673968+00:00",
  "date_archived": "2016-02-07"
}