{"record_id": "a6245d13c58f4a8c", "original_url": "http://www.cargadetrabalhos.net/2016/01/27/web-designers-designers-entrada-imediata-3-vagas/", "wayback_url": "https://arquivo.pt/noFrame/replay/20160204135348/https://www.cargadetrabalhos.net/page/3/", "arquivo_timestamp": "20160204135348", "year": 2016, "title": "web designers + designers (entrada imediata 3 vagas)", "company": "", "location": "", "date_posted": "27 / Janeiro / 2016", "source": "cargadetrabalhos", "scraped_at_utc": "2026-05-03T21:15:21.657518+00:00"}