{
  "record_id": "65712c18f5158d53",
  "year": 2021,
  "title": "Contabilista Certificado Júnior -Porto",
  "company": "",
  "location": "",
  "date_posted": "27.08.2020",
  "original_url": "https://expressoemprego.pt/emprego/contabilista-certificado-junior--porto/2009374",
  "wayback_url": "https://arquivo.pt/noFrame/replay/20210101182353/http://expressoemprego.pt/ofertas-emprego?page=12",
  "arquivo_timestamp": "20210101182353",
  "source": "neoexpresso",
  "scraped_at_utc": "2026-05-02T18:01:14.186786+00:00",
  "date_archived": "2021-01-01"
}